apyanki/__init__.py
apyanki/anki.py
apyanki/cards.py
apyanki/cli.py
apyanki/config.py
apyanki/console.py
apyanki/fields.py
apyanki/markdown_math.py
apyanki/note.py
apyanki/utilities.py
apyanki-0.18.1.dist-info/METADATA
apyanki-0.18.1.dist-info/WHEEL
apyanki-0.18.1.dist-info/entry_points.txt
apyanki-0.18.1.dist-info/licenses/LICENSE.md
apyanki-0.18.1.dist-info/RECORD
