Metadata-Version: 2.4
Name: apyanki
Version: 0.18.1
Summary: CLI script for interacting with local Anki collection
Project-URL: Homepage, https://github.com/lervag/apy
Project-URL: Bug Tracker, https://github.com/lervag/apy/issues
Author-email: Karl Yngve Lervåg <karl.yngve@lervag.net>
License-File: LICENSE.md
Classifier: Environment :: Console
Classifier: License :: OSI Approved :: MIT License
Classifier: Operating System :: OS Independent
Classifier: Programming Language :: Python :: 3
Requires-Python: >=3.10
Requires-Dist: anki>=23.10
Requires-Dist: beautifulsoup4>=4.12.2
Requires-Dist: click>=8.1.3
Requires-Dist: html5lib~=1.1
Requires-Dist: markdown>=3.4.3
Requires-Dist: markdownify>=0.11.6
Requires-Dist: readchar>=4.0.5
Requires-Dist: rich>=13.7.1
